discord.pyaio-0.16.12.dist-info/RECORD
discord.pyaio-0.16.12.dist-info/top_level.txt
discord.pyaio-0.16.12.dist-info/WHEEL
discord.pyaio-0.16.12.dist-info/metadata.json
discord.pyaio-0.16.12.dist-info/DESCRIPTION.rst
discord.pyaio-0.16.12.dist-info/METADATA
discord/invite.py
discord/emoji.py
discord/channel.py
discord/mixins.py
discord/__init__.py
discord/member.py
discord/message.py
discord/gateway.py
discord/calls.py
discord/errors.py
discord/object.py
discord/colour.py
discord/game.py
discord/compat.py
discord/utils.py
discord/http.py
discord/permissions.py
discord/user.py
discord/voice_client.py
discord/server.py
discord/client.py
discord/role.py
discord/opus.py
discord/reaction.py
discord/state.py
discord/embeds.py
discord/activity.py
discord/iterators.py
discord/enums.py
discord/bin/libopus-0.x64.dll
discord/bin/libopus-0.x86.dll
discord/ext/__init__.py
discord/ext/ipc/__init__.py
discord/ext/ipc/errors.py
discord/ext/ipc/server.py
discord/ext/ipc/protocol.py
discord/ext/ipc/client.py
discord/ext/commands/__init__.py
discord/ext/commands/formatter.py
discord/ext/commands/errors.py
discord/ext/commands/core.py
discord/ext/commands/bot.py
discord/ext/commands/cooldowns.py
discord/ext/commands/view.py
discord/ext/commands/context.py
discord/ext/commands/converter.py
