Metadata-Version: 2.0
Name: discord.pyaio
Version: 0.16.12
Summary: A python wrapper for the Discord API
Home-page: https://github.com/Rapptz/discord.py
Author: org. from Rapptz
License: MIT
Platform: UNKNOWN
Classifier: Development Status :: 4 - Beta
Classifier: License :: OSI Approved :: MIT License
Classifier: Intended Audience :: Developers
Classifier: Natural Language :: English
Classifier: Operating System :: OS Independent
Classifier: Programming Language :: Python :: 3.4
Classifier: Programming Language :: Python :: 3.5
Classifier: Topic :: Internet
Classifier: Topic :: Software Development :: Libraries
Classifier: Topic :: Software Development :: Libraries :: Python Modules
Classifier: Topic :: Utilities
Provides-Extra: voice
Requires-Dist: aiohttp (>=1.0.0,<3.1.0)
Requires-Dist: websockets (<4.0,>=3.1)
Provides-Extra: voice
Requires-Dist: PyNaCl (==1.0.1); extra == 'voice'
